setup.py
pyleida/__init__.py
pyleida/_data_loader.py
pyleida/_leida.py
pyleida.egg-info/PKG-INFO
pyleida.egg-info/SOURCES.txt
pyleida.egg-info/dependency_links.txt
pyleida.egg-info/not-zip-safe
pyleida.egg-info/requires.txt
pyleida.egg-info/top_level.txt
pyleida/clustering/__init__.py
pyleida/clustering/_clustering.py
pyleida/clustering/rsnets_overlap.py
pyleida/data_utils/__init__.py
pyleida/data_utils/_data_utils.py
pyleida/data_utils/validation.py
pyleida/dynamics_metrics/__init__.py
pyleida/dynamics_metrics/_dynamics_metrics.py
pyleida/plotting/__init__.py
pyleida/plotting/_plotting.py
pyleida/plotting/dev_surfer.py
pyleida/signal_tools/__init__.py
pyleida/signal_tools/_signal_tools.py
pyleida/stats/__init__.py
pyleida/stats/_stats.py